mlflow_sweep/__init__.py
mlflow_sweep/commands.py
mlflow_sweep/models.py
mlflow_sweep/plotting.py
mlflow_sweep/runcontext.py
mlflow_sweep/sampler.py
mlflow_sweep/sweepstate.py
mlflow_sweep/utils.py
mlflow_sweep-0.1.0.dist-info/METADATA
mlflow_sweep-0.1.0.dist-info/WHEEL
mlflow_sweep-0.1.0.dist-info/entry_points.txt
mlflow_sweep-0.1.0.dist-info/licenses/LICENSE
mlflow_sweep-0.1.0.dist-info/RECORD
