Metadata-Version: 2.4
Name: mlflow-sweep
Version: 0.1.0
Summary: Add your description here
Author-email: Nicki Skafte <skaftenicki@gmail.com>
License-File: LICENSE
Classifier: Programming Language :: Python :: 3 :: Only
Classifier: Programming Language :: Python :: 3.11
Classifier: Programming Language :: Python :: 3.12
Classifier: Programming Language :: Python :: 3.13
Requires-Python: >=3.11
Requires-Dist: click>=8.2.1
Requires-Dist: mlflow>=3.1
Requires-Dist: plotly>=6.1.2
Requires-Dist: pydantic>=2.11.5
Requires-Dist: pyyaml>=6.0.2
Requires-Dist: rich>=14
Requires-Dist: sweeps>=0.2
